turbo_ajedrez/__init__.py
turbo_ajedrez/turbo_ajedrez.py
turbo_ajedrez-0.0.3.dist-info/METADATA
turbo_ajedrez-0.0.3.dist-info/WHEEL
turbo_ajedrez-0.0.3.dist-info/top_level.txt
turbo_ajedrez-0.0.3.dist-info/zip-safe
turbo_ajedrez-0.0.3.dist-info/RECORD
